{
  "waitAfterLoadMs": 1000,
  "networkIdleTimeoutMs": 2500,
  "shots": [
    {
      "name": "toggle-default",
      "screenshot": {
        "file": "toggle-default.png",
        "fullPage": true
      }
    },
    {
      "name": "toggle-interactive",
      "reset": true,
      "actions": [
        {
          "type": "press",
          "key": "Tab"
        }
      ],
      "beforeScreenshotWaitMs": 120,
      "mustDifferFrom": "toggle-default",
      "screenshot": {
        "file": "toggle-interactive.png",
        "fullPage": true
      }
    }
  ]
}
